LICENSE
README.md
setup.py
CEEMDAN_LSTM/__init__.py
CEEMDAN_LSTM/core.py
CEEMDAN_LSTM/data_preprocessor.py
CEEMDAN_LSTM/keras_predictor.py
CEEMDAN_LSTM/sklearn_predictor.py
CEEMDAN_LSTM.egg-info/PKG-INFO
CEEMDAN_LSTM.egg-info/SOURCES.txt
CEEMDAN_LSTM.egg-info/dependency_links.txt
CEEMDAN_LSTM.egg-info/requires.txt
CEEMDAN_LSTM.egg-info/top_level.txt
CEEMDAN_LSTM/datasets/sse_index.csv