Metadata-Version: 2.1
Name: CEEMDAN-LSTM
Version: 1.2.1
Summary: CEEMDAN_LSTM is a Python project for decomposition-integration forecasting models based on EMD methods and LSTM.
Home-page: http://github.com/FateMurphy/CEEMDAN_LSTM
Author: Feite Zhou
Author-email: jupiterzhou@foxmail.com
Keywords: CEEMDAN,VMD,LSTM,decomposition,forecasting
Classifier: Development Status :: 5 - Production/Stable
Classifier: Intended Audience :: Science/Research
Classifier: Topic :: Scientific/Engineering :: Artificial Intelligence
Classifier: License :: OSI Approved :: MIT License
Classifier: Programming Language :: Python :: 3
License-File: LICENSE
